{"traceEvents":[{"pid":5325,"tid":5325,"ts":8086,"ph":"X","dur":822,"name":"Frontend"},{"pid":5325,"tid":5325,"ts":8954,"ph":"X","dur":555,"name":"Backend"},{"pid":5325,"tid":5325,"ts":22,"ph":"X","dur":9688,"name":"ExecuteCompiler"},{"pid":5325,"tid":5326,"ph":"X","ts":0,"dur":9688,"name":"Total ExecuteCompiler","args":{"count":1,"avg ms":9}},{"pid":5325,"tid":5327,"ph":"X","ts":0,"dur":855,"name":"Total Frontend","args":{"count":2,"avg ms":0}},{"pid":5325,"tid":5328,"ph":"X","ts":0,"dur":555,"name":"Total Backend","args":{"count":1,"avg ms":0}},{"pid":5325,"tid":5329,"ph":"X","ts":0,"dur":309,"name":"Total Optimizer","args":{"count":1,"avg ms":0}},{"pid":5325,"tid":5330,"ph":"X","ts":0,"dur":271,"name":"Total CodeGen Function","args":{"count":1,"avg ms":0}},{"pid":5325,"tid":5331,"ph":"X","ts":0,"dur":260,"name":"Total ThinLTOBitcodeWriterPass","args":{"count":1,"avg ms":0}},{"pid":5325,"tid":5332,"ph":"X","ts":0,"dur":184,"name":"Total ParseDeclarationOrFunctionDefinition","args":{"count":1,"avg ms":0}},{"pid":5325,"tid":5333,"ph":"X","ts":0,"dur":127,"name":"Total ParseFunctionDefinition","args":{"count":1,"avg ms":0}},{"pid":5325,"tid":5334,"ph":"X","ts":0,"dur":66,"name":"Total ModuleSummaryIndexAnalysis","args":{"count":1,"avg ms":0}},{"pid":5325,"tid":5335,"ph":"X","ts":0,"dur":48,"name":"Total BlockFrequencyAnalysis","args":{"count":1,"avg ms":0}},{"pid":5325,"tid":5336,"ph":"X","ts":0,"dur":39,"name":"Total BranchProbabilityAnalysis","args":{"count":1,"avg ms":0}},{"pid":5325,"tid":5337,"ph":"X","ts":0,"dur":20,"name":"Total ModuleToFunctionPassAdaptor","args":{"count":2,"avg ms":0}},{"pid":5325,"tid":5338,"ph":"X","ts":0,"dur":19,"name":"Total DebugType","args":{"count":1,"avg ms":0}},{"pid":5325,"tid":5339,"ph":"X","ts":0,"dur":19,"name":"Total LoopAnalysis","args":{"count":1,"avg ms":0}},{"pid":5325,"tid":5340,"ph":"X","ts":0,"dur":7,"name":"Total AnnotationRemarksPass","args":{"count":1,"avg ms":0}},{"pid":5325,"tid":5341,"ph":"X","ts":0,"dur":5,"name":"Total EvaluateAsRValue","args":{"count":1,"avg ms":0}},{"pid":5325,"tid":5342,"ph":"X","ts":0,"dur":5,"name":"Total PostDominatorTreeAnalysis","args":{"count":1,"avg ms":0}},{"pid":5325,"tid":5343,"ph":"X","ts":0,"dur":5,"name":"Total AlwaysInlinerPass","args":{"count":1,"avg ms":0}},{"pid":5325,"tid":5344,"ph":"X","ts":0,"dur":4,"name":"Total CoroConditionalWrapper","args":{"count":1,"avg ms":0}},{"pid":5325,"tid":5345,"ph":"X","ts":0,"dur":4,"name":"Total EntryExitInstrumenterPass","args":{"count":1,"avg ms":0}},{"pid":5325,"tid":5346,"ph":"X","ts":0,"dur":2,"name":"Total PerformPendingInstantiations","args":{"count":1,"avg ms":0}},{"pid":5325,"tid":5347,"ph":"X","ts":0,"dur":2,"name":"Total CanonicalizeAliasesPass","args":{"count":1,"avg ms":0}},{"pid":5325,"tid":5348,"ph":"X","ts":0,"dur":2,"name":"Total TargetLibraryAnalysis","args":{"count":1,"avg ms":0}},{"pid":5325,"tid":5349,"ph":"X","ts":0,"dur":1,"name":"Total InnerAnalysisManagerProxy<FunctionAnalysisManager, Module>","args":{"count":1,"avg ms":0}},{"pid":5325,"tid":5350,"ph":"X","ts":0,"dur":1,"name":"Total DominatorTreeAnalysis","args":{"count":1,"avg ms":0}},{"pid":5325,"tid":5351,"ph":"X","ts":0,"dur":1,"name":"Total ProfileSummaryAnalysis","args":{"count":1,"avg ms":0}},{"pid":5325,"tid":5352,"ph":"X","ts":0,"dur":1,"name":"Total NameAnonGlobalPass","args":{"count":1,"avg ms":0}},{"cat":"","pid":5325,"tid":5325,"ts":0,"ph":"M","name":"process_name","args":{"name":"clang"}},{"cat":"","pid":5325,"tid":5325,"ts":0,"ph":"M","name":"thread_name","args":{"name":"clang++-21"}}],"beginningOfTime":1776658573833389}